rtl/alu/adder32.sv
// adder32.sv
module adder32 (
    input  logic [31:0] A,
    input  logic [31:0] B,
    input  logic [1:0]  pack_mode,   // 00=word, 01=half, 10=byte
    output logic [31:0] result
);

    // Lane results
    logic [31:0] word_sum;
    logic [15:0] half_sum_lo, half_sum_hi;
    logic [7:0]  byte_sum0, byte_sum1, byte_sum2, byte_sum3;

    // Word (32-bit)
    assign word_sum = A + B;

    // Half (two 16-bit lanes)
    assign half_sum_lo = A[15:0]  + B[15:0];
    assign half_sum_hi = A[31:16] + B[31:16];

    // Byte (four 8-bit lanes)
    assign byte_sum0 = A[7:0]    + B[7:0];
    assign byte_sum1 = A[15:8]   + B[15:8];
    assign byte_sum2 = A[23:16]  + B[23:16];
    assign byte_sum3 = A[31:24]  + B[31:24];

    // Mode select
    always_comb begin
        result = '0;
        unique case (pack_mode)
            2'b00: result = word_sum;
            2'b01: result = {half_sum_hi, half_sum_lo};
            2'b10: result = {byte_sum3, byte_sum2, byte_sum1, byte_sum0};
            default: result = '0;
        endcase
    end

endmodule

rtl/alu/dump.vcd
$version Generated by VerilatedVcd $end
$timescale 1ps $end
 $scope module $rootio $end
  $var wire 32 # A [31:0] $end
  $var wire 32 $ B [31:0] $end
  $var wire 2 % pack_mode [1:0] $end
  $var wire 32 & result [31:0] $end
 $upscope $end
 $scope module adder32 $end
  $var wire 32 ' A [31:0] $end
  $var wire 32 ( B [31:0] $end
  $var wire 2 ) pack_mode [1:0] $end
  $var wire 32 * result [31:0] $end
  $var wire 32 + word_sum [31:0] $end
  $var wire 16 , half_sum_lo [15:0] $end
  $var wire 16 - half_sum_hi [15:0] $end
  $var wire 8 . byte_sum0 [7:0] $end
  $var wire 8 / byte_sum1 [7:0] $end
  $var wire 8 0 byte_sum2 [7:0] $end
  $var wire 8 1 byte_sum3 [7:0] $end
 $upscope $end
$enddefinitions $end


#0
b11111111111111111111111111111111 #
b00000000000000000000000000000001 $
b00 %
b00000000000000000000000000000000 &
b11111111111111111111111111111111 '
b00000000000000000000000000000001 (
b00 )
b00000000000000000000000000000000 *
b00000000000000000000000000000000 +
b0000000000000000 ,
b1111111111111111 -
b00000000 .
b11111111 /
b11111111 0
b11111111 1
#1000
b00000000000000000000000000000011 #
b00000000000000000000000000000100 $
b00000000000000000000000000000111 &
b00000000000000000000000000000011 '
b00000000000000000000000000000100 (
b00000000000000000000000000000111 *
b00000000000000000000000000000111 +
b0000000000000111 ,
b0000000000000000 -
b00000111 .
b00000000 /
b00000000 0
b00000000 1
#2000
b00000000000000011111111111111111 #
b00000000000000010000000000000001 $
b01 %
b00000000000000100000000000000000 &
b00000000000000011111111111111111 '
b00000000000000010000000000000001 (
b01 )
b00000000000000100000000000000000 *
b00000000000000110000000000000000 +
b0000000000000000 ,
b0000000000000010 -
b00000000 .
b11111111 /
b00000010 0
#3000
b00000000111111110000000000000000 #
b00000000000000010000000000000000 $
b10 %
b00000000000000000000000000000000 &
b00000000111111110000000000000000 '
b00000000000000010000000000000000 (
b10 )
b00000000000000000000000000000000 *
b00000001000000000000000000000000 +
b0000000100000000 -
b00000000 /
b00000000 0
#4000
b10110011100000110111000110001100 #
b10100100010101100100001011000001 $
b01 %
b01010111110110011011010001001101 &
b10110011100000110111000110001100 '
b10100100010101100100001011000001 (
b01 )
b01010111110110011011010001001101 *
b01010111110110011011010001001101 +
b1011010001001101 ,
b0101011111011001 -
b01001101 .
b10110011 /
b11011001 0
b01010111 1
#5000
b00001111000011101101011110101100 #
b01111010100100011100010000010000 $
b00 %
b10001001101000001001101110111100 &
b00001111000011101101011110101100 '
b01111010100100011100010000010000 (
b00 )
b10001001101000001001101110111100 *
b10001001101000001001101110111100 +
b1001101110111100 ,
b1000100110011111 -
b10111100 .
b10011011 /
b10011111 0
b10001001 1
#6000
b01111010000001100011111111111100 #
b00110100110111111000110000000011 $
b10 %
b10101110111001011100101111111111 &
b01111010000001100011111111111100 '
b00110100110111111000110000000011 (
b10 )
b10101110111001011100101111111111 *
b10101110111001011100101111111111 +
b1100101111111111 ,
b1010111011100101 -
b11111111 .
b11001011 /
b11100101 0
b10101110 1
#7000
b00101010000000010010110011110010 #
b10111000110110000110100010100111 $
b11100010110110011001010010011001 &
b00101010000000010010110011110010 '
b10111000110110000110100010100111 (
b11100010110110011001010010011001 *
b11100010110110011001010110011001 +
b1001010110011001 ,
b1110001011011001 -
b10011001 .
b10010100 /
b11011001 0
b11100010 1
#8000
b00010101000101101100101111100110 #
b10110110010110011001010111001001 $
b00 %
b11001011011100000110000110101111 &
b00010101000101101100101111100110 '
b10110110010110011001010111001001 (
b00 )
b11001011011100000110000110101111 *
b11001011011100000110000110101111 +
b0110000110101111 ,
b1100101101101111 -
b10101111 .
b01100000 /
b01101111 0
b11001011 1
#9000
b10110001101001111011111110111111 #
b01110101010011010111111011110010 $
b10 %
b00100110111101000011110110110001 &
b10110001101001111011111110111111 '
b01110101010011010111111011110010 (
b10 )
b00100110111101000011110110110001 *
b00100110111101010011111010110001 +
b0011111010110001 ,
b0010011011110100 -
b10110001 .
b00111101 /
b11110100 0
b00100110 1
#10000
b10010111110110010100100110011011 #
b11100111010010000011100111110010 $
b01 %
b01111111001000011000001110001101 &
b10010111110110010100100110011011 '
b11100111010010000011100111110010 (
b01 )
b01111111001000011000001110001101 *
b01111111001000011000001110001101 +
b1000001110001101 ,
b0111111100100001 -
b10001101 .
b10000010 /
b00100001 0
b01111110 1
#11000
b10110100100111111011101111111111 #
b00001011100010011110001001010101 $
b10 %
b10111111001010001001110101010100 &
b10110100100111111011101111111111 '
b00001011100010011110001001010101 (
b10 )
b10111111001010001001110101010100 *
b11000000001010011001111001010100 +
b1001111001010100 ,
b1100000000101000 -
b01010100 .
b10011101 /
b00101000 0
b10111111 1
#12000
b01110100011100010101100001011011 #
b10101000101001000010100101100110 $
b00011100000101011000000111000001 &
b01110100011100010101100001011011 '
b10101000101001000010100101100110 (
b00011100000101011000000111000001 *
b00011101000101011000000111000001 +
b1000000111000001 ,
b0001110100010101 -
b11000001 .
b10000001 /
b00010101 0
b00011100 1
#13000
b10010100010101100111000011011101 #
b00011100100001010011111110100000 $
b01 %
b10110000110110111011000001111101 &
b10010100010101100111000011011101 '
b00011100100001010011111110100000 (
b01 )
b10110000110110111011000001111101 *
b10110000110110111011000001111101 +
b1011000001111101 ,
b1011000011011011 -
b01111101 .
b10101111 /
b11011011 0
b10110000 1
#14000
b10100111110101000001001101110001 #
b00110100101011011000001000101011 $
b11011100100000011001010110011100 &
b10100111110101000001001101110001 '
b00110100101011011000001000101011 (
b11011100100000011001010110011100 *
b11011100100000011001010110011100 +
b1001010110011100 ,
b1101110010000001 -
b10011100 .
b10010101 /
b10000001 0
b11011011 1
#15000
b01101011001001011010100001110000 #
b00100011000010010000001110010101 $
b00 %
b10001110001011101010110000000101 &
b01101011001001011010100001110000 '
b00100011000010010000001110010101 (
b00 )
b10001110001011101010110000000101 *
b10001110001011101010110000000101 +
b1010110000000101 ,
b1000111000101110 -
b00000101 .
b10101011 /
b00101110 0
b10001110 1
#16000
b10101001111111000100000110111111 #
b01011100001010100100110100111011 $
b00000110001001101000111011111010 &
b10101001111111000100000110111111 '
b01011100001010100100110100111011 (
b00000110001001101000111011111010 *
b00000110001001101000111011111010 +
b1000111011111010 ,
b0000011000100110 -
b11111010 .
b10001110 /
b00100110 0
b00000101 1
#17000
b01101110110001101100110101010100 #
b00010011111001100001101110011000 $
b10 %
b10000001101011001110100011101100 &
b01101110110001101100110101010100 '
b00010011111001100001101110011000 (
b10 )
b10000001101011001110100011101100 *
b10000010101011001110100011101100 +
b1110100011101100 ,
b1000001010101100 -
b11101100 .
b11101000 /
b10101100 0
b10000001 1
#18000
b01000101100100110111100111010011 #
b10010100100100011111010000011101 $
b11011001001001000110110111110000 &
b01000101100100110111100111010011 '
b10010100100100011111010000011101 (
b11011001001001000110110111110000 *
b11011010001001010110110111110000 +
b0110110111110000 ,
b1101101000100100 -
b11110000 .
b01101101 /
b00100100 0
b11011001 1
#19000
b10000000101010101101001101010100 #
b00010101111001100110011100011100 $
b10010101100100000011101001110000 &
b10000000101010101101001101010100 '
b00010101111001100110011100011100 (
b10010101100100000011101001110000 *
b10010110100100010011101001110000 +
b0011101001110000 ,
b1001011010010000 -
b01110000 .
b00111010 /
b10010000 0
b10010101 1
#20000
b10011000111010001001110110100001 #
b01000000001011000001000010011001 $
b00 %
b11011001000101001010111000111010 &
b10011000111010001001110110100001 '
b01000000001011000001000010011001 (
b00 )
b11011001000101001010111000111010 *
b11011001000101001010111000111010 +
b1010111000111010 ,
b1101100100010100 -
b00111010 .
b10101101 /
b00010100 0
b11011000 1
#21000
b10001101001101000101100110101010 #
b11110000001000101011110001001100 $
b01111101010101110001010111110110 &
b10001101001101000101100110101010 '
b11110000001000101011110001001100 (
b01111101010101110001010111110110 *
b01111101010101110001010111110110 +
b0001010111110110 ,
b0111110101010110 -
b11110110 .
b00010101 /
b01010110 0
b01111101 1
#22000
b01000110011111111110011011110111 #
b10110011101011111110010111100111 $
b11111010001011111100110011011110 &
b01000110011111111110011011110111 '
b10110011101011111110010111100111 (
b11111010001011111100110011011110 *
b11111010001011111100110011011110 +
b1100110011011110 ,
b1111101000101110 -
b11011110 .
b11001011 /
b00101110 0
b11111001 1
#23000
b01110010011010111001111100001001 #
b00010101011010101110111101101111 $
b10 %
b10000111110101011000111001111000 &
b01110010011010111001111100001001 '
b00010101011010101110111101101111 (
b10 )
b10000111110101011000111001111000 *
b10000111110101101000111001111000 +
b1000111001111000 ,
b1000011111010101 -
b01111000 .
b10001110 /
b11010101 0
b10000111 1
#24000
b00101000001010111110000001101101 #
b00110001101010110100000010101101 $
b01 %
b01011001110101100010000100011010 &
b00101000001010111110000001101101 '
b00110001101010110100000010101101 (
b01 )
b01011001110101100010000100011010 *
b01011001110101110010000100011010 +
b0010000100011010 ,
b0101100111010110 -
b00011010 .
b00100000 /
b11010110 0
b01011001 1
#25000
b11101000111011010101111100011110 #
b00001011111010010000011010110001 $
b11110100110101100110010111001111 &
b11101000111011010101111100011110 '
b00001011111010010000011010110001 (
b11110100110101100110010111001111 *
b11110100110101100110010111001111 +
b0110010111001111 ,
b1111010011010110 -
b11001111 .
b01100101 /
b11110011 1
#26000
b11100010010101011100100101011111 #
b11010011011111111111111110111100 $
b00 %
b10110101110101011100100100011011 &
b11100010010101011100100101011111 '
b11010011011111111111111110111100 (
b00 )
b10110101110101011100100100011011 *
b10110101110101011100100100011011 +
b1100100100011011 ,
b1011010111010100 -
b00011011 .
b11001000 /
b11010100 0
b10110101 1
#27000
b11010101111000111101011000100110 #
b10110010100110000101111101001001 $
b01 %
b10001000011110110011010101101111 &
b11010101111000111101011000100110 '
b10110010100110000101111101001001 (
b01 )
b10001000011110110011010101101111 *
b10001000011111000011010101101111 +
b0011010101101111 ,
b1000100001111011 -
b01101111 .
b00110101 /
b01111011 0
b10000111 1
#28000
b01000001101111111010100010101100 #
b10011011111100011111000010000111 $
b00 %
b11011101101100011001100100110011 &
b01000001101111111010100010101100 '
b10011011111100011111000010000111 (
b00 )
b11011101101100011001100100110011 *
b11011101101100011001100100110011 +
b1001100100110011 ,
b1101110110110000 -
b00110011 .
b10011000 /
b10110000 0
b11011100 1
#29000
b01000101111110100011101100101000 #
b10110111110110011111100101110000 $
b10 %
b11111100110100110011010010011000 &
b01000101111110100011101100101000 '
b10110111110110011111100101110000 (
b10 )
b11111100110100110011010010011000 *
b11111101110101000011010010011000 +
b0011010010011000 ,
b1111110111010011 -
b10011000 .
b00110100 /
b11010011 0
b11111100 1
#30000
b10011010001100101111111000110101 #
b00011100100110110101010000010110 $
b10110110110011010101001001001011 &
b10011010001100101111111000110101 '
b00011100100110110101010000010110 (
b10110110110011010101001001001011 *
b10110110110011100101001001001011 +
b0101001001001011 ,
b1011011011001101 -
b01001011 .
b01010010 /
b11001101 0
b10110110 1
#31000
b11111100110010011111011111110010 #
b00100110110111001101010011001011 $
b01 %
b00100011101001011100110010111101 &
b11111100110010011111011111110010 '
b00100110110111001101010011001011 (
b01 )
b00100011101001011100110010111101 *
b00100011101001101100110010111101 +
b1100110010111101 ,
b0010001110100101 -
b10111101 .
b11001011 /
b10100101 0
b00100010 1
#32000
b00011010000101110001111011001000 #
b01001010111010010110001110100111 $
b00 %
b01100101000000001000001001101111 &
b00011010000101110001111011001000 '
b01001010111010010110001110100111 (
b00 )
b01100101000000001000001001101111 *
b01100101000000001000001001101111 +
b1000001001101111 ,
b0110010100000000 -
b01101111 .
b10000001 /
b00000000 0
b01100100 1
#33000
b10000100000011100001010101110011 #
b01010100101100100101011011100100 $
b10 %
b11011000110000000110101101010111 &
b10000100000011100001010101110011 '
b01010100101100100101011011100100 (
b10 )
b11011000110000000110101101010111 *
b11011000110000000110110001010111 +
b0110110001010111 ,
b1101100011000000 -
b01010111 .
b01101011 /
b11000000 0
b11011000 1
#34000
b10000111100011001100110111010011 #
b11010001111101101110010010110001 $
b00 %
b01011001100000111011001010000100 &
b10000111100011001100110111010011 '
b11010001111101101110010010110001 (
b00 )
b01011001100000111011001010000100 *
b01011001100000111011001010000100 +
b1011001010000100 ,
b0101100110000010 -
b10000100 .
b10110001 /
b10000010 0
b01011000 1
#35000
b01100110100110010011110101001010 #
b11000001100001000011011100010111 $
b00101000000111010111010001100001 &
b01100110100110010011110101001010 '
b11000001100001000011011100010111 (
b00101000000111010111010001100001 *
b00101000000111010111010001100001 +
b0111010001100001 ,
b0010100000011101 -
b01100001 .
b01110100 /
b00011101 0
b00100111 1
#36000
b10011011100001000011010010111001 #
b01101111010111000011101011000101 $
b01 %
b00001010111000000110111101111110 &
b10011011100001000011010010111001 '
b01101111010111000011101011000101 (
b01 )
b00001010111000000110111101111110 *
b00001010111000000110111101111110 +
b0110111101111110 ,
b0000101011100000 -
b01111110 .
b01101110 /
b11100000 0
b00001010 1
#37000
b11011101010011100000110000010000 #
b10101111101001000111111010000010 $
b10 %
b10001100111100101000101010010010 &
b11011101010011100000110000010000 '
b10101111101001000111111010000010 (
b10 )
b10001100111100101000101010010010 *
b10001100111100101000101010010010 +
b1000101010010010 ,
b1000110011110010 -
b10010010 .
b10001010 /
b11110010 0
b10001100 1
#38000
b10011111110110001010100010110110 #
b11000101010111011110100110000011 $
b01100100001101011001000100111001 &
b10011111110110001010100010110110 '
b11000101010111011110100110000011 (
b01100100001101011001000100111001 *
b01100101001101101001001000111001 +
b1001001000111001 ,
b0110010100110101 -
b00111001 .
b10010001 /
b00110101 0
b01100100 1
#39000
b00100001101011101000001011011110 #
b10000111101111111001011000010011 $
b00 %
b10101001011011100001100011110001 &
b00100001101011101000001011011110 '
b10000111101111111001011000010011 (
b00 )
b10101001011011100001100011110001 *
b10101001011011100001100011110001 +
b0001100011110001 ,
b1010100101101101 -
b11110001 .
b00011000 /
b01101101 0
b10101000 1
#40000
b01011001111011010011110010101100 #
b11011101110110011000010010010001 $
b10 %
b00110110110001101100000000111101 &
b01011001111011010011110010101100 '
b11011101110110011000010010010001 (
b10 )
b00110110110001101100000000111101 *
b00110111110001101100000100111101 +
b1100000100111101 ,
b0011011111000110 -
b00111101 .
b11000000 /
b11000110 0
b00110110 1
#41000
b10000010011010011100110001000101 #
b01001111101100010001001011011001 $
b11010001000110101101111000011110 &
b10000010011010011100110001000101 '
b01001111101100010001001011011001 (
b11010001000110101101111000011110 *
b11010010000110101101111100011110 +
b1101111100011110 ,
b1101001000011010 -
b00011110 .
b11011110 /
b00011010 0
b11010001 1
#42000
b00011111001110110010101010100011 #
b00110100010001000111100101110101 $
b00 %
b01010011011111111010010000011000 &
b00011111001110110010101010100011 '
b00110100010001000111100101110101 (
b00 )
b01010011011111111010010000011000 *
b01010011011111111010010000011000 +
b1010010000011000 ,
b0101001101111111 -
b00011000 .
b10100011 /
b01111111 0
b01010011 1
#43000
b00011001000110110010000101000110 #
b00011110010110011011000100000100 $
b00110111011101001101001001001010 &
b00011001000110110010000101000110 '
b00011110010110011011000100000100 (
b00110111011101001101001001001010 *
b00110111011101001101001001001010 +
b1101001001001010 ,
b0011011101110100 -
b01001010 .
b11010010 /
b01110100 0
b00110111 1
#44000
b01000101101011001011111101100111 #
b01010010000111101110001111111001 $
b10010111110010111010001101100000 &
b01000101101011001011111101100111 '
b01010010000111101110001111111001 (
b10010111110010111010001101100000 *
b10010111110010111010001101100000 +
b1010001101100000 ,
b1001011111001010 -
b01100000 .
b10100010 /
b11001010 0
b10010111 1
#45000
b00101101101000101111100011001110 #
b00011100110010010111010110110010 $
b01001010011011000110111010000000 &
b00101101101000101111100011001110 '
b00011100110010010111010110110010 (
b01001010011011000110111010000000 *
b01001010011011000110111010000000 +
b0110111010000000 ,
b0100101001101011 -
b10000000 .
b01101101 /
b01101011 0
b01001001 1
#46000
b01110011101110010001000101001111 #
b11000111110100001010011000111110 $
b00111011100010011011011110001101 &
b01110011101110010001000101001111 '
b11000111110100001010011000111110 (
b00111011100010011011011110001101 *
b00111011100010011011011110001101 +
b1011011110001101 ,
b0011101110001001 -
b10001101 .
b10110111 /
b10001001 0
b00111010 1
#47000
b10011110010000011101101110100100 #
b00011100101011000100100001011101 $
b10111010111011100010010000000001 &
b10011110010000011101101110100100 '
b00011100101011000100100001011101 (
b10111010111011100010010000000001 *
b10111010111011100010010000000001 +
b0010010000000001 ,
b1011101011101101 -
b00000001 .
b00100011 /
b11101101 0
b10111010 1
#48000
b11010010001010100000011011100001 #
b10111000011010000100011000000101 $
b10001010100100100100110011100110 &
b11010010001010100000011011100001 '
b10111000011010000100011000000101 (
b10001010100100100100110011100110 *
b10001010100100100100110011100110 +
b0100110011100110 ,
b1000101010010010 -
b11100110 .
b01001100 /
b10010010 0
b10001010 1
#49000
b01001011111011010010111010000100 #
b00101001101100100110100010000011 $
b10 %
b01110100100111111001011000000111 &
b01001011111011010010111010000100 '
b00101001101100100110100010000011 (
b10 )
b01110100100111111001011000000111 *
b01110101100111111001011100000111 +
b1001011100000111 ,
b0111010110011111 -
b00000111 .
b10010110 /
b10011111 0
b01110100 1
#50000
b11011010110001010110001011100110 #
b11001011101001000101101111010011 $
b10100101011010011011110110111001 &
b11011010110001010110001011100110 '
b11001011101001000101101111010011 (
b10100101011010011011110110111001 *
b10100110011010011011111010111001 +
b1011111010111001 ,
b1010011001101001 -
b10111001 .
b10111101 /
b01101001 0
b10100101 1
#51000
b00010010010001011000111000111111 #
b01110101001011001100010010101000 $
b10000111011100010101001011100111 &
b00010010010001011000111000111111 '
b01110101001011001100010010101000 (
b10000111011100010101001011100111 *
b10000111011100100101001011100111 +
b0101001011100111 ,
b1000011101110001 -
b11100111 .
b01010010 /
b01110001 0
b10000111 1
#52000
b00101111010101011101101001101110 #
b11101000110101110000101110111010 $
b00 %
b00011000001011001110011000101000 &
b00101111010101011101101001101110 '
b11101000110101110000101110111010 (
b00 )
b00011000001011001110011000101000 *
b00011000001011001110011000101000 +
b1110011000101000 ,
b0001100000101100 -
b00101000 .
b11100101 /
b00101100 0
b00010111 1
#53000
b00010110010010101111110110101111 #
b00001001001001000100010001010110 $
b10 %
b00011111011011100100000100000101 &
b00010110010010101111110110101111 '
b00001001001001000100010001010110 (
b10 )
b00011111011011100100000100000101 *
b00011111011011110100001000000101 +
b0100001000000101 ,
b0001111101101110 -
b00000101 .
b01000001 /
b01101110 0
b00011111 1
#54000
b10010000111000110010011100011100 #
b11000101101110000101100010011000 $
b01 %
b01010110100110110111111110110100 &
b10010000111000110010011100011100 '
b11000101101110000101100010011000 (
b01 )
b01010110100110110111111110110100 *
b01010110100110110111111110110100 +
b0111111110110100 ,
b0101011010011011 -
b10110100 .
b01111111 /
b10011011 0
b01010101 1
#55000
b11011011110000110110100001101110 #
b01101110010110100011000101011010 $
b01001010000111011001100111001000 &
b11011011110000110110100001101110 '
b01101110010110100011000101011010 (
b01001010000111011001100111001000 *
b01001010000111011001100111001000 +
b1001100111001000 ,
b0100101000011101 -
b11001000 .
b10011001 /
b00011101 0
b01001001 1
#56000
b10100001101011001100001110001000 #
b10111011001100000111110011101000 $
b01011100110111000100000001110000 &
b10100001101011001100001110001000 '
b10111011001100000111110011101000 (
b01011100110111000100000001110000 *
b01011100110111010100000001110000 +
b0100000001110000 ,
b0101110011011100 -
b01110000 .
b00111111 /
b11011100 0
b01011100 1
#57000
b11001000110101110110100000100111 #
b01110010110101101110110010011111 $
b10 %
b00111010101011010101010011000110 &
b11001000110101110110100000100111 '
b01110010110101101110110010011111 (
b10 )
b00111010101011010101010011000110 *
b00111011101011100101010011000110 +
b0101010011000110 ,
b0011101110101101 -
b11000110 .
b01010100 /
b10101101 0
b00111010 1
#58000
b01110110001010000110111100011110 #
b00100111101111001001110110111111 $
b00 %
b10011101111001010000110011011101 &
b01110110001010000110111100011110 '
b00100111101111001001110110111111 (
b00 )
b10011101111001010000110011011101 *
b10011101111001010000110011011101 +
b0000110011011101 ,
b1001110111100100 -
b11011101 .
b00001100 /
b11100100 0
b10011101 1
#59000
b00010011000110101111100000101011 #
b00111101000001101110000111101100 $
b01010000001000011101101000010111 &
b00010011000110101111100000101011 '
b00111101000001101110000111101100 (
b01010000001000011101101000010111 *
b01010000001000011101101000010111 +
b1101101000010111 ,
b0101000000100000 -
b00010111 .
b11011001 /
b00100000 0
b01010000 1
#60000
b10110011010101101000110000010111 #
b00011101000101000110011011000100 $
b10 %
b11010000011010101111001011011011 &
b10110011010101101000110000010111 '
b00011101000101000110011011000100 (
b10 )
b11010000011010101111001011011011 *
b11010000011010101111001011011011 +
b1111001011011011 ,
b1101000001101010 -
b11011011 .
b11110010 /
b01101010 0
b11010000 1
#61000
b11011111010101000100001000011010 #
b00100111010101111101110111001100 $
b01 %
b00000110101010110001111111100110 &
b11011111010101000100001000011010 '
b00100111010101111101110111001100 (
b01 )
b00000110101010110001111111100110 *
b00000110101011000001111111100110 +
b0001111111100110 ,
b0000011010101011 -
b11100110 .
b00011111 /
b10101011 0
b00000110 1
#62000
b10100010101010110110101111100001 #
b00101110101011011100010001101111 $
b00 %
b11010001010110010011000001010000 &
b10100010101010110110101111100001 '
b00101110101011011100010001101111 (
b00 )
b11010001010110010011000001010000 *
b11010001010110010011000001010000 +
b0011000001010000 ,
b1101000101011000 -
b01010000 .
b00101111 /
b01011000 0
b11010000 1
#63000
b01000000000000001111110010110011 #
b10001011110000011000010100101010 $
b01 %
b11001011110000011000000111011101 &
b01000000000000001111110010110011 '
b10001011110000011000010100101010 (
b01 )
b11001011110000011000000111011101 *
b11001011110000101000000111011101 +
b1000000111011101 ,
b1100101111000001 -
b11011101 .
b10000001 /
b11000001 0
b11001011 1
#64000
b01010000110011111001010100110110 #
b10000011101001000011100001000010 $
b11010100011100111100110101111000 &
b01010000110011111001010100110110 '
b10000011101001000011100001000010 (
b11010100011100111100110101111000 *
b11010100011100111100110101111000 +
b1100110101111000 ,
b1101010001110011 -
b01111000 .
b11001101 /
b01110011 0
b11010011 1
#65000
b11111001101001111110000110011010 #
b00110100101001100101101110100101 $
b10 %
b00101101010011010011110000111111 &
b11111001101001111110000110011010 '
b00110100101001100101101110100101 (
b10 )
b00101101010011010011110000111111 *
b00101110010011100011110100111111 +
b0011110100111111 ,
b0010111001001101 -
b00111111 .
b00111100 /
b01001101 0
b00101101 1
#66000
b00110010110101011101001110000000 #
b01110111000111011111010101010110 $
b01 %
b10101001111100101100100011010110 &
b00110010110101011101001110000000 '
b01110111000111011111010101010110 (
b01 )
b10101001111100101100100011010110 *
b10101001111100111100100011010110 +
b1100100011010110 ,
b1010100111110010 -
b11010110 .
b11001000 /
b11110010 0
b10101001 1
#67000
b10001100111111111001100001111011 #
b00111110010101110100101000101000 $
b10 %
b11001010010101101110001010100011 &
b10001100111111111001100001111011 '
b00111110010101110100101000101000 (
b10 )
b11001010010101101110001010100011 *
b11001011010101101110001010100011 +
b1110001010100011 ,
b1100101101010110 -
b10100011 .
b11100010 /
b01010110 0
b11001010 1
#68000
b00001010001001100100100110011011 #
b11001011010010100001001010111101 $
b01 %
b11010101011100000101110001011000 &
b00001010001001100100100110011011 '
b11001011010010100001001010111101 (
b01 )
b11010101011100000101110001011000 *
b11010101011100000101110001011000 +
b0101110001011000 ,
b1101010101110000 -
b01011000 .
b01011011 /
b01110000 0
b11010101 1
#69000
b11010011000001001010101100011100 #
b10010010100010011101011110101110 $
b10 %
b01100101100011011000001011001010 &
b11010011000001001010101100011100 '
b10010010100010011101011110101110 (
b10 )
b01100101100011011000001011001010 *
b01100101100011101000001011001010 +
b1000001011001010 ,
b0110010110001101 -
b11001010 .
b10000010 /
b10001101 0
b01100101 1
#70000
b11010010111011101111110101010110 #
b01101101011001110111100010101011 $
b01 %
b01000000010101010111011000000001 &
b11010010111011101111110101010110 '
b01101101011001110111100010101011 (
b01 )
b01000000010101010111011000000001 *
b01000000010101100111011000000001 +
b0111011000000001 ,
b0100000001010101 -
b00000001 .
b01110101 /
b01010101 0
b00111111 1
#71000
b10110111100011111101101011101101 #
b11001110010100000101000101000110 $
b00 %
b10000101111000000010110000110011 &
b10110111100011111101101011101101 '
b11001110010100000101000101000110 (
b00 )
b10000101111000000010110000110011 *
b10000101111000000010110000110011 +
b0010110000110011 ,
b1000010111011111 -
b00110011 .
b00101011 /
b11011111 0
b10000101 1
#72000
b11001000110110011011110111001001 #
b01101100000011010100100101010011 $
b10 %
b00110100111001100000011000011100 &
b11001000110110011011110111001001 '
b01101100000011010100100101010011 (
b10 )
b00110100111001100000011000011100 *
b00110100111001110000011100011100 +
b0000011100011100 ,
b0011010011100110 -
b00011100 .
b00000110 /
b11100110 0
b00110100 1
#73000
b01000001011000110111000000001101 #
b11010000100100001010001011000011 $
b01 %
b00010001111100110001001011010000 &
b01000001011000110111000000001101 '
b11010000100100001010001011000011 (
b01 )
b00010001111100110001001011010000 *
b00010001111101000001001011010000 +
b0001001011010000 ,
b0001000111110011 -
b11010000 .
b00010010 /
b11110011 0
b00010001 1
#74000
b01001111010010100101110100101110 #
b10001111001001110110000100111011 $
b11011110011100011011111001101001 &
b01001111010010100101110100101110 '
b10001111001001110110000100111011 (
b11011110011100011011111001101001 *
b11011110011100011011111001101001 +
b1011111001101001 ,
b1101111001110001 -
b01101001 .
b10111110 /
b01110001 0
b11011110 1
#75000
b01000000110101001101001111110111 #
b01101011111110000111001111101000 $
b10101100110011000100011111011111 &
b01000000110101001101001111110111 '
b01101011111110000111001111101000 (
b10101100110011000100011111011111 *
b10101100110011010100011111011111 +
b0100011111011111 ,
b1010110011001100 -
b11011111 .
b01000110 /
b11001100 0
b10101011 1
#76000
b10111110011110100110111101001101 #
b10111000000000001001110010010101 $
b10 %
b01110110011110100000101111100010 &
b10111110011110100110111101001101 '
b10111000000000001001110010010101 (
b10 )
b01110110011110100000101111100010 *
b01110110011110110000101111100010 +
b0000101111100010 ,
b0111011001111010 -
b11100010 .
b00001011 /
b01111010 0
b01110110 1
#77000
b11010011111111100101001111111111 #
b10100110100011001110100011101100 $
b00 %
b01111010100010110011110011101011 &
b11010011111111100101001111111111 '
b10100110100011001110100011101100 (
b00 )
b01111010100010110011110011101011 *
b01111010100010110011110011101011 +
b0011110011101011 ,
b0111101010001010 -
b11101011 .
b00111011 /
b10001010 0
b01111001 1
#78000
b11111111111001111110111100001011 #
b10011000010010111010110010100010 $
b10 %
b10010111001100101001101110101101 &
b11111111111001111110111100001011 '
b10011000010010111010110010100010 (
b10 )
b10010111001100101001101110101101 *
b10011000001100111001101110101101 +
b1001101110101101 ,
b1001100000110010 -
b10101101 .
b10011011 /
b00110010 0
b10010111 1
#79000
b00001111011110000011100111111110 #
b10010101111010111101010011111010 $
b10100100011000110000110111111000 &
b00001111011110000011100111111110 '
b10010101111010111101010011111010 (
b10100100011000110000110111111000 *
b10100101011001000000111011111000 +
b0000111011111000 ,
b1010010101100011 -
b11111000 .
b00001101 /
b01100011 0
b10100100 1
#80000
b01010100010010100110011100110011 #
b10011110011100000100010110100110 $
b11110010101110101010110011011001 &
b01010100010010100110011100110011 '
b10011110011100000100010110100110 (
b11110010101110101010110011011001 *
b11110010101110101010110011011001 +
b1010110011011001 ,
b1111001010111010 -
b11011001 .
b10101100 /
b10111010 0
b11110010 1
#81000
b10010000000111110101100111010001 #
b00010011110101110000110101100110 $
b01 %
b10100011111101100110011100110111 &
b10010000000111110101100111010001 '
b00010011110101110000110101100110 (
b01 )
b10100011111101100110011100110111 *
b10100011111101100110011100110111 +
b0110011100110111 ,
b1010001111110110 -
b00110111 .
b01100110 /
b11110110 0
b10100011 1
#82000
b10111110010000000000110111010100 #
b11001001101000110100100110011111 $
b10 %
b10000111111000110101011001110011 &
b10111110010000000000110111010100 '
b11001001101000110100100110011111 (
b10 )
b10000111111000110101011001110011 *
b10000111111000110101011101110011 +
b0101011101110011 ,
b1000011111100011 -
b01110011 .
b01010110 /
b11100011 0
b10000111 1
#83000
b00111110100011111001001011011101 #
b01110100110111011001101010011011 $
b10110010011011000010110001111000 &
b00111110100011111001001011011101 '
b01110100110111011001101010011011 (
b10110010011011000010110001111000 *
b10110011011011010010110101111000 +
b0010110101111000 ,
b1011001101101100 -
b01111000 .
b00101100 /
b01101100 0
b10110010 1
#84000
b00001110101101011000010101011011 #
b11101011110010000100101011111011 $
b01 %
b11111010011111011101000001010110 &
b00001110101101011000010101011011 '
b11101011110010000100101011111011 (
b01 )
b11111010011111011101000001010110 *
b11111010011111011101000001010110 +
b1101000001010110 ,
b1111101001111101 -
b01010110 .
b11001111 /
b01111101 0
b11111001 1
